MANIFEST.in
README.rst
setup.py
src/django_iframetoolbox.egg-info/PKG-INFO
src/django_iframetoolbox.egg-info/SOURCES.txt
src/django_iframetoolbox.egg-info/dependency_links.txt
src/django_iframetoolbox.egg-info/not-zip-safe
src/django_iframetoolbox.egg-info/top_level.txt
src/iframetoolbox/__init__.py
src/iframetoolbox/middleware.py
src/iframetoolbox/models.py
src/iframetoolbox/tests.py
src/iframetoolbox/urls.py
src/iframetoolbox/views.py
src/iframetoolbox/templates/iframe/cookie_page.html
src/iframetoolbox/templates/iframe/cookie_warning.html