Metadata-Version: 1.1
Name: django-iframetoolbox
Version: 0.2.1
Summary: Django set of tools to work inside iframe
Home-page: http://www.aurumsocial.com
Author: Domantas Jackūnas
Author-email: Domantas.Jackunas@aurumsocial.com
License: BSD
Download-URL: https://bitbucket.org/JackLeo/django-iframetoolbox/
Keywords: iframe django safari fix
Platform: UNKNOWN
Classifier: Development Status :: 3 - Alpha
Classifier: Environment :: Web Environment
Classifier: Framework :: Django
Classifier: Intended Audience :: Developers
Classifier: License :: OSI Approved :: BSD License
Classifier: Programming Language :: Python
Classifier: Topic :: Software Development :: Libraries :: Python Modules
